smeagol/__init__.py
smeagol/aggregate.py
smeagol/encode.py
smeagol/enrich.py
smeagol/io.py
smeagol/matrices.py
smeagol/models.py
smeagol/scan.py
smeagol/utils.py
smeagol/variant.py
smeagol/visualize.py
smeagol_bio-0.1.1.dist-info/LICENSE
smeagol_bio-0.1.1.dist-info/METADATA
smeagol_bio-0.1.1.dist-info/WHEEL
smeagol_bio-0.1.1.dist-info/top_level.txt
smeagol_bio-0.1.1.dist-info/RECORD
