Metadata-Version: 2.1
Name: smeagol-bio
Version: 0.1.1
Summary: UNKNOWN
Home-page: UNKNOWN
License: UNKNOWN
Platform: any
Requires-Python: >=3.7, !=3.9
Requires-Dist: biopython (>=1.79)
Requires-Dist: h5py (>=3.1.0)
Requires-Dist: keras (>=2.4.3)
Requires-Dist: numpy (>=1.19.2)
Requires-Dist: pandas (>=1.2.5)
Requires-Dist: pytest (>=6.2.4)
Requires-Dist: recommonmark (>=0.7.1)
Requires-Dist: scikit-learn (>=0.24.2)
Requires-Dist: scipy (>=1.7.0)
Requires-Dist: seaborn (>=0.11.1)
Requires-Dist: setuptools (>=57.0.0)
Requires-Dist: sphinx (>=5.0.0)
Requires-Dist: statsmodels (>=0.12.2)
Requires-Dist: tables (>=3.6.1)
Requires-Dist: tensorflow (>=2.5.0)
Requires-Dist: deeplift (>=0.6.13.0)
